AUTHORS
ChangeLog
LICENSE
Readme.rst
requirements.txt
setup.cfg
setup.py
tox.ini
compose_monitor/__init__.py
compose_monitor/logger.py
compose_monitor/main.py
compose_monitor/monitor.py
compose_monitor.egg-info/PKG-INFO
compose_monitor.egg-info/SOURCES.txt
compose_monitor.egg-info/dependency_links.txt
compose_monitor.egg-info/entry_points.txt
compose_monitor.egg-info/not-zip-safe
compose_monitor.egg-info/pbr.json
compose_monitor.egg-info/requires.txt
compose_monitor.egg-info/top_level.txt