Metadata-Version: 1.1
Name: compose-monitor
Version: 1.2.4
Summary: This utility is designed for monitoring and updating of the services in the specified docker-compose.yml file.
Home-page: https://github.com/FromZeus/compose-monitor
Author: Daniil Trishkin
Author-email: asteroid566@gmail.com
License: UNKNOWN
Platform: UNKNOWN
Classifier: Intended Audience :: Information Technology
Classifier: Intended Audience :: System Administrators
Classifier: License :: OSI Approved :: Apache Software License
Classifier: Operating System :: POSIX :: Linux
Classifier: Programming Language :: Python
Classifier: Programming Language :: Python :: 2
Classifier: Programming Language :: Python :: 2.7
